{
   "Общие параметры": {
      " Тип ": " кулер для процессора",
      " Модель ": " Arctic Cooling Freezer 34 eSports DUO",
      " Код производителя ": " [ACFRE00060A]",
      " Сокет ": " AM4, LGA 1150, LGA 1151, LGA 1151-v2, LGA 1155, LGA 1156, LGA 1200, LGA 2011, LGA 2011-3, LGA 2066",
      " Рассеиваемая мощность ": " 210 Вт",
      " Тип конструкции ": "башенный"
   },
   "Радиатор": {
      " Материал основания ": "алюминий\\медь",
      " Материал радиатора ": "алюминий",
      " Количество тепловых трубок ": " 4",
      " Диаметр тепловых трубок ": " 6 мм",
      " Никелированное покрытие ": " нет",
      " Цвет радиатора ": " черный"
   },
   "Вентилятор": {
      " Количество вентиляторов в комплекте ": " 2",
      " Максимальное число устанавливаемых вентиляторов ": " 2",
      " Размеры комплектных вентиляторов ": " 120 x 120 мм",
      " Цвет вентилятора ": " красный, черный",
      " Разъем для подключения вентиляторов ": "4 pin",
      " Максимальная скорость вращения ": " 2100 об/мин",
      " Минимальная скорость вращения ": " 200 об/мин",
      " Регулировка скорости вращения ": "автоматическая (PWM)",
      " Максимальный уровень шума ": " 28 дБ",
      " Номинальный ток ": " 0.26 А",
      " Номинальное напряжение ": " 12 В",
      " Тип подшипника ": " скольжения (гидродинамический)"
   },
   "Дополнительно": {
      " Термопаста в комплекте ": " в отдельной емкости",
      " Тип подсветки ": " нет",
      " Комплектация ": " документация, комплект крепления"
   },
   "Габариты, вес": {
      " Высота ": " 157 мм",
      " Ширина ": " 124 мм",
      " Длина ": " 103 мм",
      " Вес ": " 764 г"
   },
   "Описание": "Башенный кулер для процессора Arctic Cooling Freezer 34 eSports DUO [ACFRE00060A] – отличный вариант для использования в составе компьютера, уровень производительности которого заметно превышает средний. Вы сможете гарантировать безопасную и стабильную работу процессора высокого класса. В списке совместимости – 10 сокетов (все, кроме AM4 – Intel).  Кулер Arctic Cooling Freezer 34 eSports DUO [ACFRE00060A] оборудован двумя 120-миллиметровыми вентиляторами, частота вращения которых может изменяться от 200 до 2100 оборотов в минуту. Уровень шума невысок: величина данного показателя не превышает 28 дБ. Даже при отсутствии других источников шума процессорный кулер не будет доставлять неудобства.  Особенность дизайна кулера – вставки красного цвета. Подсветка отсутствует. В комплектацию устройства входят документация, крепления и термопаста.",
   "Цена": "5091 ₽"
}