{
   "Общие параметры": {
      " Тип ": "2.5\" SATA накопитель",
      " Модель ": " ADATA SU750",
      " Код производителя ": " [ASU750SS-1TT-C]"
   },
   "Основные характеристики": {
      " Объем накопителя ": " 1000 ГБ",
      " NVMe ": " нет",
      " Разъем подключения ": " SATA"
   },
   "Конфигурация накопителя": {
      " Количество бит на ячейку ": "3 бит TLC",
      " Структура памяти ": "3D NAND",
      " DRAM буфер ": " есть",
      " Объем DRAM буфера ": " 32 МБ"
   },
   "Показатели производительности": {
      " Максимальная скорость последовательного чтения ": " 550 Мбайт/сек",
      " Максимальная скорость последовательной записи ": " 520 Мбайт/сек",
      " Скорость произвольного чтения 4 Кб файлов (QD32) ": " 65000 IOPS",
      " Скорость произвольной записи 4 Кб файлов (QD32) ": " 75000 IOPS"
   },
   "Надежность": {
      " Максимальный ресурс записи (TBW) ": " 800 ТБ",
      " DWPD ": " 0.71",
      " Максимальная перегрузка (ударостойкость) ": " 1500 G"
   },
   "Дополнительная информация": {
      " Комплектация ": " документация"
   },
   "Габариты": {
      " Ширина ": " 69.85 мм",
      " Длина ": " 100.45 мм",
      " Толщина ": " 7 мм",
      " Вес ": " 47.5 г"
   },
   "Описание": "1024 ГБ SSD-накопитель A-Data SU750 [ASU750SS-1TT-C] может стать надежной и эффективной основой файловой системы вашего компьютера. Благодаря чипам NAND, используемым в основе данной модели, а также производительному контроллеру обеспечивается высокое быстродействие при обработке различных данных. Для подключения диска к компьютеру используется интерфейс SATA III с пропускной способностью до 6 Гбит/с, за счет чего скорость записи и чтения файлов может достигать 520 и 550 МБ/с соответственно. Также модель отличается высокой надежностью и большим ресурсом, который соответствует 800 TBW, что обеспечивает продолжительную работу и сохранность данных.  SSD-накопитель A-Data SU750 [ASU750SS-1TT-C] выполнен в корпусе формата 2.5” с шириной 69.85 мм, длиной 100 мм и толщиной 7 мм. Благодаря своим размерам данная модель может устанавливаться как в настольные компьютеры, так и ноутбуки, а при помощи специального кейса, докупаемого отдельно, диск может использоваться как внешнее устройство для удобной работы с файлами.",
   "Цена": "3572 ₽"
}