{
   "Общие параметры": {
      " Тип ": "2.5\" SATA накопитель",
      " Модель ": " Team Group GX2",
      " Код производителя ": " [T253X2256G0C101]"
   },
   "Основные характеристики": {
      " Объем накопителя ": " 256 ГБ",
      " NVMe ": " нет",
      " Разъем подключения ": " SATA"
   },
   "Конфигурация накопителя": {
      " Количество бит на ячейку ": "3 бит TLC",
      " Структура памяти ": "3D NAND",
      " DRAM буфер ": " нет"
   },
   "Показатели производительности": {
      " Максимальная скорость последовательного чтения ": " 500 Мбайт/сек",
      " Максимальная скорость последовательной записи ": " 400 Мбайт/сек"
   },
   "Надежность": {
      " Максимальный ресурс записи (TBW) ": " 200 ТБ",
      " DWPD ": " 0.71",
      " Максимальная перегрузка (ударостойкость) ": " 1500 G"
   },
   "Дополнительная информация": {
      " Аппаратное шифрование данных ": " нет",
      " Комплектация ": " документация"
   },
   "Габариты": {
      " Ширина ": " 69.9 мм",
      " Длина ": " 100 мм",
      " Толщина ": " 7 мм",
      " Вес ": " 43 г"
   },
   "Описание": "256 ГБ SSD-накопитель Team Group GX2 [T253X2256G0C101] оборудован разъемом подключения SATA III и предназначен для применения в пользовательской домашней станции или игровом ПК. Ускоряющий загрузку любых приложений накопитель поддерживает считывание со скоростью до 500 МБайт/сек, а запись осуществляется на скоростях до 400 МБайт/сек. Оптимальное для использования в качестве логического диска устройство долговременной памяти получило контроллер Silicon Motion SM2258XT, за счет которого осуществляется управление ячейками памяти типа NAND.  2.5-дюймовый SSD-накопитель Team Group GX2 [T253X2256G0C101] объемом 256 ГБ имеет значимые преимущества в виде бесшумности работы, низкого уровня нагрева, малого потребления энергии. Эта модель поддерживает питание через интерфейс SATA 15 pin. Рабочий ресурс такого накопителя оценивается производителем на уровне 200 TBW.",
   "Цена": "5431 ₽"
}