{
   "Общие параметры": {
      " Тип ": " видеокарта",
      " Модель ": " PowerColor AMD Radeon RX 6700 Fighter OC",
      " Код производителя ": " [AXRX 6700 10GBD6-3DH/OC]",
      " Цвет ": " черный",
      " Предназначена для майнинга (добыча криптовалют) ": " нет",
      " LHR ": " нет"
   },
   "Основные параметры": {
      " Графический процессор ": " Radeon RX 6700",
      " Микроархитектура ": " AMD RDNA 2",
      " Техпроцесс ": " 7 нм"
   },
   "Спецификации видеопамяти": {
      " Объем видеопамяти ": " 10 ГБ",
      " Тип памяти ": "GDDR6",
      " Разрядность шины памяти ": " 160 бит",
      " Максимальная пропускная способность памяти ": " 320 Гбайт/сек",
      " Эффективная частота памяти ": " 16000 МГц"
   },
   "Спецификации видеопроцессора": {
      " Штатная частота работы видеочипа ": " 1941 МГц",
      " Турбочастота ": " 2495 МГц",
      " Количество универсальных процессоров (ALU) ": " 2304",
      " Число текстурных блоков ": " 144",
      " Число блоков растеризации ": " 64",
      " Поддержка трассировки лучей ": " есть",
      " Аппаратное ускорение трассировки лучей (RT-ядра) ": " 36",
      " Версия шейдеров ": "6.4"
   },
   "Вывод изображения": {
      " Видеоразъемы ": " DisplayPort x3, HDMI",
      " Версия HDMI ": "2.1",
      " Версия DisplayPort ": "1.4",
      " Количество подключаемых одновременно мониторов ": " 4",
      " Максимальное разрешение ": " Ultra HD 8K (7680x4320)"
   },
   "Подключение": {
      " Интерфейс подключения ": "PCI-E 4.0",
      " Форм-фактор разъема подключения ": " PCI-E x16",
      " Разъемы дополнительного питания ": " 8-pin + 6-pin",
      " Рекомендуемый блок питания ": " 650 Вт"
   },
   "Система охлаждения": {
      " Тип охлаждения ": "активное воздушное",
      " Тип и количество установленных вентиляторов ": " 2 осевых",
      " Радиатор жидкостного охлаждения ": " нет"
   },
   "Габариты и вес": {
      " Низкопрофильная карта (Low Profile) ": " нет",
      " Количество занимаемых слотов расширения ": " 2",
      " Длина видеокарты ": " 228 мм",
      " Ширина видеокарты ": " 109 мм",
      " Толщина видеокарты ": " 32 мм"
   },
   "Дополнительно": {
      " Подсветка элементов видеокарты ": " нет",
      " Синхронизация RGB подсветки ": " нет",
      " LCD дисплей ": " нет",
      " Переключатель BIOS ": " нет",
      " Комплектация ": " документация"
   },
   "Описание": "Видеокарта PowerColor AMD Radeon RX 6700 Fighter OC станет надежным решением для установки в геймерские ПК. Благодаря архитектуре AMD RDNA 2.0 с 36 мощными вычислительными блоками, кэш-памятью AMD Infinity Cache и скоростной памятью стандарта GDDR6 10 ГБ достигается высокая производительность в играх с высокой частотой кадров и плавностью динамичных сцен. Тактовая частота процессора составляет в пределах 2495 МГц в режиме разгона.  Возможности подключения видеокарты PowerColor AMD Radeon RX 6700 Fighter OC представлены 3 разъемами DisplayPort и 1 разъемом HDMI. Активное охлаждение с двумя вентиляторами, радиатором и медными тепловыми трубками быстро рассеивает тепло для защиты от чрезмерного нагрева. На задней стороне для повышения стойкости к деформации и повреждения установлена металлическая пластина.",
   "Цена": "3513 ₽"
}