{
   "Общие параметры": {
      " Тип ": " корпус",
      " Модель ": " AeroCool Ore-G",
      " Код производителя ": " [Ore Saturn FRGB-G-BK-v1]"
   },
   "Форм-фактор и габариты": {
      " Типоразмер корпуса ": "Mid-Tower",
      " Ориентация материнской платы ": " вертикально",
      " Длина ": " 422 мм",
      " Ширина ": " 195 мм",
      " Высота ": " 461 мм"
   },
   "Внешний вид": {
      " Основной цвет ": " черный",
      " Материал корпуса ": "пластик, сталь, стекло",
      " Толщина металла ": " 0.5 мм",
      " Наличие окна на боковой стенке ": " слева",
      " Материал окна ": "закаленное стекло",
      " Материал фронтальной панели ": " металлическая сетка, пластик",
      " Тип подсветки ": " FRGB",
      " Цвет подсветки ": " многоцветная",
      " Источник подсветки ": " вентилятор",
      " Разъем подключения подсветки ": " Molex"
   },
   "Совместимость": {
      " Форм-фактор совместимых плат ": " Micro-ATX, Mini-ITX, Standard-ATX",
      " Форм-фактор совместимых блоков питания ": " ATX",
      " Размещение блока питания ": " нижнее",
      " Максимальная длина блока питания ": " 206 мм",
      " Горизонтальные слоты расширения ": " 7",
      " Вертикальные слоты расширения ": " нет",
      " Максимальная длина устанавливаемой видеокарты ": " 371 мм",
      " Максимальная высота процессорного кулера ": " 155 мм",
      " Количество отсеков 2.5\" накопителей ": " 5 шт",
      " Число внутренних отсеков 3.5\" ": " 2 шт",
      " Число внешних отсеков 3.5\" ": " нет",
      " Число отсеков 5.25\" ": " нет"
   },
   "Охлаждение": {
      " Вентиляторы в комплекте ": " 3 x 120 мм",
      " Поддержка фронтальных вентиляторов ": " 3 x 120 мм",
      " Поддержка тыловых вентиляторов ": " 1 x 120 мм",
      " Поддержка верхних вентиляторов ": " нет",
      " Поддержка нижних вентиляторов ": " 2 x 120 мм",
      " Поддержка боковых вентиляторов ": " нет",
      " Возможность установки системы жидкостного охлаждения ": " есть",
      " Фронтальный монтажный размер радиатора СЖО ": " 120 мм, 240 мм"
   },
   "Разъемы и интерфейсы лицевой панели": {
      " Расположение I/O панели ": " сверху",
      " Разъемы ": " 3.5 мм jack (аудио), 3.5 мм jack (микрофон), USB 2.0 Type-A x2, USB 3.2 Gen1 Type-A",
      " Встроенный кард-ридер ": " есть"
   },
   "Обслуживание": {
      " Фиксация боковых панелей ": " винты сбоку",
      " Вырез в районе крепления кулера CPU ": " есть",
      " Прокладка кабелей за задней стенкой ": " есть"
   },
   "Дополнительная информация": {
      " Встроенный БП ": " нет",
      " Малошумные и антивибрационные корпуса ": " нет",
      " Комплектация ": " документация, набор крепежа"
   },
   "Описание": "Корпус AeroCool Ore-G [Ore Saturn FRGB-G-BK-v1] относится к популярному формату Mid-Tower. В нем можно собрать компоненты высокопроизводительного ПК. Внутрь корпуса можно установить мат. платы Micro-ATX, Mini-ITX, Standard-ATX, видеокарты длиной до 371 мм и кулеры высотой до 15.5 см.  За счет 3 предусмотренных вентиляторов и жидкостного охлаждения, которое можно установить при желании, они будут своевременно охлаждаться. Изготовлен корпус из пластика и 0.5-миллиметровой стали. Благодаря тому, что боковая стенка выполнена из закаленного стекла, все компоненты, красиво подсвеченные светодиодами, можно видеть снаружи. Сетчатый дизайн лицевой панели усиливает вентиляцию.",
   "Цена": [
      "4 999 ₽",
      "4 999 ₽"
   ]
}