{
   "Общие параметры": {
      " Тип ": " корпус",
      " Модель ": " AeroCool Cylon WG"
   },
   "Форм-фактор и габариты": {
      " Типоразмер корпуса ": "Mid-Tower",
      " Ориентация материнской платы ": " вертикально",
      " Длина ": " 413 мм",
      " Ширина ": " 198 мм",
      " Высота ": " 459 мм",
      " Вес ": " 3.8 кг"
   },
   "Внешний вид": {
      " Основной цвет ": " белый",
      " Дополнительные цвета ": " черный",
      " Материал корпуса ": "пластик, сталь",
      " Толщина металла ": " 0.5 мм",
      " Наличие окна на боковой стенке ": " слева",
      " Материал окна ": "закаленное стекло",
      " Материал фронтальной панели ": " пластик",
      " Тип подсветки ": " RGB",
      " Цвет подсветки ": " многоцветная",
      " Источник подсветки ": " корпус",
      " Способ управления подсветкой ": " кнопка на корпусе"
   },
   "Совместимость": {
      " Форм-фактор совместимых плат ": " Micro-ATX, Mini-ITX, Standard-ATX",
      " Форм-фактор совместимых блоков питания ": " ATX",
      " Размещение блока питания ": " нижнее",
      " Максимальная длина блока питания ": " 207 мм",
      " Горизонтальные слоты расширения ": " 7",
      " Вертикальные слоты расширения ": " нет",
      " Максимальная длина устанавливаемой видеокарты ": " 371 мм",
      " Максимальная высота процессорного кулера ": " 155 мм",
      " Количество отсеков 2.5\" накопителей ": " 2 шт",
      " Число внутренних отсеков 3.5\" ": " 2 шт",
      " Число внешних отсеков 3.5\" ": " нет",
      " Число отсеков 5.25\" ": " нет"
   },
   "Охлаждение": {
      " Вентиляторы в комплекте ": " 1 x 120 мм",
      " Поддержка фронтальных вентиляторов ": " 2 x 140 или 3 x 120 мм",
      " Поддержка тыловых вентиляторов ": " 1 x 120 мм",
      " Поддержка верхних вентиляторов ": " 1 x 120 мм",
      " Поддержка нижних вентиляторов ": " нет",
      " Поддержка боковых вентиляторов ": " нет",
      " Возможность установки системы жидкостного охлаждения ": " есть",
      " Фронтальный монтажный размер радиатора СЖО ": " 120 мм"
   },
   "Разъемы и интерфейсы лицевой панели": {
      " Расположение I/O панели ": " сверху",
      " Разъемы ": " 3.5 мм jack (аудио), 3.5 мм jack (микрофон), USB 2.0 Type-A x2, USB 3.2 Gen1 Type-A",
      " Встроенный кард-ридер ": " есть"
   },
   "Обслуживание": {
      " Фиксация боковых панелей ": " винты сбоку",
      " Вырез в районе крепления кулера CPU ": " есть",
      " Прокладка кабелей за задней стенкой ": " есть",
      " Пылевой фильтр ": " есть"
   },
   "Дополнительная информация": {
      " Встроенный БП ": " нет",
      " Малошумные и антивибрационные корпуса ": " нет",
      " Комплектация ": " документация, набор крепежа"
   },
   "Описание": "Корпус AeroCool Cylon [4718009152342] может с успехом использоваться в качестве основы для игрового компьютера высокого класса. Блок питания вы сможете выбрать по своему усмотрению: в комплект он не входит. Максимально допустимая длина видеоадаптера равна 371 мм. Максимальная высота кулера процессора – 155 мм.  Корпус AeroCool Cylon [4718009152342] чрезвычайно эффектен. Цвет модели – белый. Передняя панель корпуса украшена эффектной многоцветной подсветкой. Отдельное внимание на себя обращает наличие карт-ридера, позволяющего использовать карты памяти microSD и SD. Эти сменные носители информации являются самыми распространенными в настоящее время.  Конструкцией корпуса предусмотрены 7 слотов расширения. Теплоотвод обеспечивает 120-миллиметровый вентилятор. Есть возможность монтажа дополнительных вентиляторов. Два 120-миллиметровых вентилятора могут использоваться для охлаждения видеокарт. Длина, ширина и высота корпуса равны 459, 198 и 413 мм соответственно. Масса модели равна 3.8 кг. В комплекте – документация и набор крепежных винтов.",
   "Цена": "4375 ₽"
}