{
   "Общие параметры": {
      " Тип ": " корпус",
      " Модель ": " AeroCool Cylon Mini BG"
   },
   "Форм-фактор и габариты": {
      " Типоразмер корпуса ": "Mini-Tower",
      " Ориентация материнской платы ": " вертикально",
      " Длина ": " 373 мм",
      " Ширина ": " 186 мм",
      " Высота ": " 381.5 мм",
      " Вес ": " 2.6 кг"
   },
   "Внешний вид": {
      " Основной цвет ": " черный",
      " Материал корпуса ": "сталь, стекло",
      " Толщина металла ": " 0.6 мм",
      " Наличие окна на боковой стенке ": " слева",
      " Материал окна ": "закаленное стекло",
      " Материал фронтальной панели ": " пластик",
      " Тип подсветки ": " RGB",
      " Цвет подсветки ": " многоцветная",
      " Источник подсветки ": " корпус",
      " Способ управления подсветкой ": " кнопка на корпусе"
   },
   "Совместимость": {
      " Форм-фактор совместимых плат ": " Micro-ATX, Mini-ITX",
      " Форм-фактор совместимых блоков питания ": " ATX",
      " Размещение блока питания ": " нижнее",
      " Максимальная длина блока питания ": " 180 мм",
      " Горизонтальные слоты расширения ": " 4",
      " Вертикальные слоты расширения ": " нет",
      " Максимальная длина устанавливаемой видеокарты ": " 300 мм",
      " Максимальная высота процессорного кулера ": " 147 мм",
      " Количество отсеков 2.5\" накопителей ": " 3 шт",
      " Число внутренних отсеков 3.5\" ": " 2 шт",
      " Число внешних отсеков 3.5\" ": " нет",
      " Число отсеков 5.25\" ": " нет"
   },
   "Охлаждение": {
      " Вентиляторы в комплекте ": " 1 x 80 мм",
      " Поддержка фронтальных вентиляторов ": " 2 x 120 мм",
      " Поддержка тыловых вентиляторов ": " 1 x 90 или 1 x 80 мм",
      " Поддержка верхних вентиляторов ": " нет",
      " Поддержка нижних вентиляторов ": " нет",
      " Поддержка боковых вентиляторов ": " нет",
      " Возможность установки системы жидкостного охлаждения ": " нет"
   },
   "Разъемы и интерфейсы лицевой панели": {
      " Расположение I/O панели ": " сверху",
      " Разъемы ": " 3.5 мм jack (аудио), 3.5 мм jack (микрофон), USB 2.0 Type-A, USB 3.2 Gen1 Type-A",
      " Встроенный кард-ридер ": " нет"
   },
   "Обслуживание": {
      " Фиксация боковых панелей ": " винты сбоку",
      " Вырез в районе крепления кулера CPU ": " есть",
      " Прокладка кабелей за задней стенкой ": " есть",
      " Пылевой фильтр ": " есть"
   },
   "Дополнительная информация": {
      " Встроенный БП ": " нет",
      " Малошумные и антивибрационные корпуса ": " нет",
      " Комплектация ": " документация"
   },
   "Описание": "Корпус Aerocool Cylon Mini BG [4718009152359] обращает на себя внимание эффектным дизайном, главной отличительной чертой которого является многоцветная подсветка, «пронизывающая» переднюю панель. Заслуживает внимания и боковое окно из закаленного стекла. Цвет корпуса (черный) можно назвать классическим.  Корпус Aerocool Cylon Mini BG [4718009152359] соответствует типоразмеру Mini-Tower. Модель совместима с материнскими платами форм-факторов Micro-ATX и Mini-ITX. Обычным предназначением корпуса является исполнение роли основы компактного универсального домашнего компьютера.  Важными параметрами корпуса являются максимальная длина устанавливаемой видеокарты (300 мм) и максимальная высота кулера процессора (147 мм). Комплектный 80-миллиметровый вентилятор можно дополнить двумя 120-миллиметровыми фронтальными вентиляторами. Блока питания в комплекте нет. Источник питания выбирается пользователем в зависимости от технических условий. Длина, ширина и высота корпуса равны 381.5, 186 и 373 мм соответственно. Масса модели – лишь 2.6 кг. В комплект поставки включена документация.",
   "Цена": [
      "3 699 ₽",
      "3 699 ₽"
   ]
}