{
   "Общие параметры": {
      " Тип ": "оперативная память",
      " Модель ": " ADATA",
      " Код производителя ": " [AD4U26664G19-SGN]"
   },
   "Объем и состав комплекта": {
      " Тип памяти ": "DDR4",
      " Форм-фактор памяти ": "DIMM",
      " Суммарный объем памяти всего комплекта ": " 4 ГБ",
      " Объем одного модуля памяти ": " 4 ГБ",
      " Количество модулей в комплекте ": " 1",
      " Регистровая память ": " нет",
      " ECC-память ": " нет"
   },
   "Быстродействие": {
      " Тактовая частота ": " 2666 МГц"
   },
   "Тайминги": {
      " CAS Latency (CL) ": " 19",
      " RAS to CAS Delay (tRCD) ": " 19",
      " Row Precharge Delay (tRP) ": " 19"
   },
   "Конструкция": {
      " Наличие радиатора ": " нет",
      " Подсветка элементов платы ": " нет",
      " Высота ": " 31.25 мм",
      " Низкопрофильная (Low Profile) ": " нет"
   },
   "Дополнительно": {
      " Напряжение питания ": " 1.2 В"
   },
   "Описание": "4-гигабайтная оперативная память A-Data [AD4U26664G19-SGN] совместима с любыми материнскими платами, рассчитанными на установку модулей DDR4. Устройство, произведенное с использованием зеленого текстолита, понравится любителям традиционного дизайна компьютерных компонентов. Память рассчитана на эксплуатацию в составе системных блоков начального и среднего уровня.  Тактовая частота памяти A-Data [AD4U26664G19-SGN] – 2666 МГц. Поддерживаются и другие режимы работы – 1600, 1866, 2133 и 2400 МГц. Память, использующая стандартное для DDR4 напряжение питания (1.2 В), демонстрирует низкое энергопотребление. Лишенный радиатора модуль имеет типовую (3.125 см) высоту.",
   "Цена": "5513 ₽"
}