{
   "Классификация": {
      " Тип ": " система охлаждения",
      " Модель ": " Fractal Design Lumen S24 RGB",
      " Код производителя ": " [FD-W-L1-S2402]",
      " Обслуживаемая СЖО ": " нет"
   },
   "Внешний вид": {
      " Основной цвет ": " черный",
      " Тип подсветки ": " RGB",
      " Источник подсветки ": " вентилятор, водоблок",
      " Разъем подключения подсветки ": " 3-pin 5V-D-G (ARGB)",
      " LCD дисплей ": " нет"
   },
   "Водоблок": {
      " Назначение ": " для процессора",
      " Сокет ": " AM2, AM2+, AM3, AM3+, AM4, FM1, FM2, FM2+, LGA 1150, LGA 1151, LGA 1151-v2, LGA 1155, LGA 1156, LGA 1200, LGA 1366, LGA 2011, LGA 2011-v3, LGA 2066",
      " Материал водоблока ": "медь",
      " Размеры водоблока ": " 79 x 67 x 43 мм"
   },
   "Радиатор": {
      " Монтажный размер радиатора ": " 120 мм - две секции",
      " Длина радиатора ": " 272 мм",
      " Ширина радиатора ": " 120 мм",
      " Толщина радиатора ": " 27 мм",
      " Материал радиатора ": "алюминий"
   },
   "Вентиляторы": {
      " Количество вентиляторов в комплекте ": " 2",
      " Размеры вентиляторов ": " 120 x 120 мм",
      " Тип подшипника вентилятора ": "скольжения (с винтовой нарезкой)",
      " Минимальная скорость вращения ": " 500 об/мин",
      " Максимальная скорость вращения ": " 2000 об/мин",
      " Регулировка скорости вращения вентилятора ": "автоматическая (PWM)",
      " Минимальный уровень шума ": " 10 дБ",
      " Максимальный уровень шума ": " 33.2 дБ",
      " Максимальный воздушный поток ": " 56 CFM",
      " Максимальное статическое давление ": " 22.9 Па",
      " Разъем подключения вентиляторов ": " 4 pin"
   },
   "Помпа": {
      " Уровень шума помпы ": " 22 дБ",
      " Скорость вращения помпы ": " 4000 об/мин",
      " Разъем подключения помпы ": " 3 pin"
   },
   "Трубки": {
      " Длина трубок ": " 400 мм",
      " Материал трубок ": " резина",
      " Прозрачные трубки ": " нет"
   },
   "Дополнительно": {
      " Особенности, дополнительно ": " набор крепежных винтов",
      " Термопаста в комплекте ": " нанесена на основание"
   },
   "Описание": "Жидкостная система охлаждения Fractal Design Lumen S24 RGB обеспечивает безопасное и эффективное функционирование производительного процессора. Модель пригодится владельцам CPU AMD и Intel. Устройство обладает совместимостью с большим (почти два десятка) количеством сокетов.  Система охлаждения Fractal Design Lumen S24 RGB оборудована парой 120-миллиметровых вентиляторов, частота вращения которых меняется в широком (от 500 до 2000 оборотов в минуту) диапазоне. Регулировка скорости вращения осуществляется в автоматическом режиме. Максимальный воздушный поток одного вентилятора составляет значительные 56 CFM. Уровень шума при этом относительно невысок – 33.2 дБ. Система охлаждения гарантированно не доставит пользователю акустический дискомфорт.  Установка системы упрощена за счет значительной (400 мм) длины гибких резиновых трубок. Главная особенность внешнего вида устройства – многоцветная подсветка, интегрированная в вентиляторы и водоблок. Система является необслуживаемой. Это означает, что устройство не рассчитано на замену компонентов и охлаждающей жидкости.",
   "Цена": "5192 ₽"
}